MANIFEST.in
README.rst
setup.py
plotutils/__init__.py
plotutils/plotutils.py
plotutils.egg-info/PKG-INFO
plotutils.egg-info/SOURCES.txt
plotutils.egg-info/dependency_links.txt
plotutils.egg-info/not-zip-safe
plotutils.egg-info/requires.txt
plotutils.egg-info/top_level.txt