Metadata-Version: 1.1
Name: plotutils
Version: 0.3.2
Summary: Simple matplotlib-related utility functions.
Home-page: https://github.com/timothydmorton/plotutils
Author: Timothy D. Morton
Author-email: tim.morton@gmail.com
License: UNKNOWN
Platform: UNKNOWN
Classifier: Development Status :: 3 - Alpha
Classifier: Intended Audience :: Science/Research
Classifier: License :: OSI Approved :: GNU General Public License (GPL)
Classifier: Operating System :: OS Independent
Classifier: Programming Language :: Python
